django_planetscale/__init__.py
django_planetscale/base.py
django_planetscale/features.py
django_planetscale-0.2.3.dist-info/LICENSE
django_planetscale-0.2.3.dist-info/WHEEL
django_planetscale-0.2.3.dist-info/METADATA
django_planetscale-0.2.3.dist-info/RECORD
